gabo/__init__.py
gabo-0.0.0.1.dist-info/METADATA
gabo-0.0.0.1.dist-info/RECORD
gabo-0.0.0.1.dist-info/WHEEL
gabo-0.0.0.1.dist-info/top_level.txt
