Metadata-Version: 2.1
Name: gabo
Version: 0.0.0.1
Summary: A CMS management tool
Home-page: https://github.com/MacondoSystems/gabo/
Author: Andres Lujan
Author-email: info@andresroot.co
License: UNKNOWN
Keywords: cms,django,privacy
Platform: UNKNOWN
Classifier: Programming Language :: Python :: 3
Classifier: License :: OSI Approved :: GNU General Public License v3 (GPLv3)
Classifier: Operating System :: OS Independent
